pxweb/__init__.py
pxweb-0.0.0.dist-info/METADATA
pxweb-0.0.0.dist-info/WHEEL
pxweb-0.0.0.dist-info/top_level.txt
pxweb-0.0.0.dist-info/RECORD
